django_copy_tables/__init__.py
django_copy_tables/apps.py
django_copy_tables/management/__init__.py
django_copy_tables/management/commands/__init__.py
django_copy_tables/management/commands/copyTables.py
django_copy_tables-0.1.9.dist-info/LICENSE
django_copy_tables-0.1.9.dist-info/METADATA
django_copy_tables-0.1.9.dist-info/WHEEL
django_copy_tables-0.1.9.dist-info/top_level.txt
django_copy_tables-0.1.9.dist-info/RECORD
