Metadata-Version: 2.1
Name: django-copy-tables
Version: 0.1.9
Summary: Library to add a view (server) and management command (client) to copy model data
Home-page: https://github.com/paradxum/django-copy-tables
Author: Eric Schultz
Author-email: eric.schultz@cyvon.com
Classifier: Programming Language :: Python :: 3
Classifier: License :: OSI Approved :: GNU General Public License v3 (GPLv3)
Classifier: Operating System :: OS Independent
Requires-Python: >=3.1
License-File: LICENSE
